Metadata-Version: 2.1
Name: torchdyn-sphinx-theme
Version: 1.0.3
Summary: Torchdyn Sphinx Theme
Home-page: https://github.com/zdenek-syntensor/torchdyn_sphinx_theme
Author: Syntensor
Author-email: zdenek@syntensor.com
License: MIT License
Classifier: Development Status :: 5 - Production/Stable
Classifier: Environment :: Web Environment
Classifier: Intended Audience :: Developers
Classifier: Intended Audience :: System Administrators
Classifier: License :: OSI Approved :: MIT License
Classifier: Operating System :: OS Independent
Classifier: Programming Language :: Python
Classifier: Topic :: Internet
Classifier: Topic :: Software Development :: Documentation
License-File: LICENSE
Requires-Dist: sphinx
